mdform/__init__.py
mdform/extension.py
mdform/fields.py
mdform/testsuite/__init__.py
mdform/testsuite/test_extension.py
mdform/testsuite/test_fields.py
mdform-0.6.dist-info/AUTHORS
mdform-0.6.dist-info/LICENSE
mdform-0.6.dist-info/METADATA
mdform-0.6.dist-info/WHEEL
mdform-0.6.dist-info/top_level.txt
mdform-0.6.dist-info/RECORD
