Metadata-Version: 2.1
Name: mdform
Version: 0.6
Summary: Parse Markdown form and generate useful templates and data.
Author-email: "Hernán E. Grecco" <hernan.grecco@gmail.com>
License: Copyright (c) 2021 by Hernan E. Grecco and contributors.  See AUTHORS
Project-URL: Homepage, https://github.com/hgrecco/mdform
Project-URL: Bug Tracker, https://github.com/hgrecco/mdform/issues
Keywords: markdown,form
Classifier: Development Status :: 4 - Beta
Classifier: Intended Audience :: Developers
Classifier: License :: OSI Approved :: BSD License
Classifier: Operating System :: MacOS :: MacOS X
Classifier: Operating System :: Microsoft :: Windows
Classifier: Operating System :: POSIX
Classifier: Topic :: Text Processing :: Markup :: HTML
Classifier: Programming Language :: Python
Classifier: Programming Language :: Python :: 3
Classifier: Programming Language :: Python :: 3.8
Classifier: Programming Language :: Python :: 3.9
Classifier: Programming Language :: Python :: 3.10
Classifier: Programming Language :: Python :: 3.11
Requires-Python: >=3.8
License-File: LICENSE
License-File: AUTHORS
Requires-Dist: markdown (>=3.0.1)
Requires-Dist: unidecode
Requires-Dist: dataclass-wizard
Provides-Extra: test
Requires-Dist: pytest ; extra == 'test'
